lastmile_utils/lib/core/api_file.py
lastmile_utils/lib/core/configs.py
lastmile_utils/lib/core/functional.py
lastmile_utils/lib/core/lm_result.py
lastmile_utils/lib/core/module_mocking.py
lastmile_utils/lib/core/utils.py
lastmile_utils/lib/core/api/__init__.py
lastmile_utils/lib/jupyter/__init__.py
lastmile_utils/lib/jupyter/utils.py
scripts/lint.py
lastmile_utils-0.0.26.dist-info/METADATA
lastmile_utils-0.0.26.dist-info/WHEEL
lastmile_utils-0.0.26.dist-info/top_level.txt
lastmile_utils-0.0.26.dist-info/RECORD
